[
    {
        "model": "participant_app.language",
        "pk": "Mandarin",
        "fields": {}
    },
    {
        "model": "participant_app.language",
        "pk": "Spanish",
        "fields": {}
    },
    {
        "model": "participant_app.language",
        "pk": "English",
        "fields": {}
    },
    {
        "model": "participant_app.language",
        "pk": "Hindi",
        "fields": {}
    },
    {
        "model": "participant_app.language",
        "pk": "Arabic",
        "fields": {}
    },
    {
        "model": "participant_app.language",
        "pk": "Portuguese",
        "fields": {}
    },
    {
        "model": "participant_app.language",
        "pk": "Bengali (Bangla)",
        "fields": {}
    },
    {
        "model": "participant_app.language",
        "pk": "Russian",
        "fields": {}
    },
    {
        "model": "participant_app.language",
        "pk": "Japanese",
        "fields": {}
    },
    {
        "model": "participant_app.language",
        "pk": "Punjabi",
        "fields": {}
    },
    {
        "model": "participant_app.language",
        "pk": "German",
        "fields": {}
    },
    {
        "model": "participant_app.language",
        "pk": "Javanese",
        "fields": {}
    },
    {
        "model": "participant_app.language",
        "pk": "Wu (inc Shanghainese)",
        "fields": {}
    },
    {
        "model": "participant_app.language",
        "pk": "Malay (inc Indonesian and Malaysian)",
        "fields": {}
    },
    {
        "model": "participant_app.language",
        "pk": "Korean",
        "fields": {}
    },
    {
        "model": "participant_app.language",
        "pk": "Telugu",
        "fields": {}
    },
    {
        "model": "participant_app.language",
        "pk": "Vietnamese",
        "fields": {}
    },
    {
        "model": "participant_app.language",
        "pk": "French",
        "fields": {}
    },
    {
        "model": "participant_app.language",
        "pk": "Marathi",
        "fields": {}
    },
    {
        "model": "participant_app.language",
        "pk": "Tamil",
        "fields": {}
    },
    {
        "model": "participant_app.language",
        "pk": "Urdu",
        "fields": {}
    },
    {
        "model": "participant_app.language",
        "pk": "Turkish",
        "fields": {}
    },
    {
        "model": "participant_app.language",
        "pk": "Italian",
        "fields": {}
    },
    {
        "model": "participant_app.language",
        "pk": "Yue (inc Cantonese)",
        "fields": {}
    },
    {
        "model": "participant_app.language",
        "pk": "Thai",
        "fields": {}
    },
    {
        "model": "participant_app.language",
        "pk": "Gujarati",
        "fields": {}
    },
    {
        "model": "participant_app.language",
        "pk": "Jin",
        "fields": {}
    },
    {
        "model": "participant_app.language",
        "pk": "Southern Min (inc Hokkien and Teochew)",
        "fields": {}
    },
    {
        "model": "participant_app.language",
        "pk": "Persian",
        "fields": {}
    },
    {
        "model": "participant_app.language",
        "pk": "Polish",
        "fields": {}
    },
    {
        "model": "participant_app.language",
        "pk": "Pashto",
        "fields": {}
    },
    {
        "model": "participant_app.language",
        "pk": "Kannada",
        "fields": {}
    },
    {
        "model": "participant_app.language",
        "pk": "Malayalam",
        "fields": {}
    },
    {
        "model": "participant_app.language",
        "pk": "Sundanese",
        "fields": {}
    },
    {
        "model": "participant_app.language",
        "pk": "Xiang",
        "fields": {}
    },
    {
        "model": "participant_app.language",
        "pk": "Hausa",
        "fields": {}
    },
    {
        "model": "participant_app.language",
        "pk": "Burmese",
        "fields": {}
    },
    {
        "model": "participant_app.language",
        "pk": "Odia (Oriya)",
        "fields": {}
    },
    {
        "model": "participant_app.language",
        "pk": "Hakka",
        "fields": {}
    },
    {
        "model": "participant_app.language",
        "pk": "Ukrainian",
        "fields": {}
    },
    {
        "model": "participant_app.language",
        "pk": "Bhojpuri",
        "fields": {}
    },
    {
        "model": "participant_app.language",
        "pk": "Tagalog (Filipino)",
        "fields": {}
    },
    {
        "model": "participant_app.language",
        "pk": "Yoruba",
        "fields": {}
    },
    {
        "model": "participant_app.language",
        "pk": "Maithili",
        "fields": {}
    },
    {
        "model": "participant_app.language",
        "pk": "Sindhi",
        "fields": {}
    },
    {
        "model": "participant_app.language",
        "pk": "Uzbek",
        "fields": {}
    },
    {
        "model": "participant_app.language",
        "pk": "Amharic",
        "fields": {}
    },
    {
        "model": "participant_app.language",
        "pk": "Fula",
        "fields": {}
    },
    {
        "model": "participant_app.language",
        "pk": "Igbo",
        "fields": {}
    },
    {
        "model": "participant_app.language",
        "pk": "Oromo",
        "fields": {}
    },
    {
        "model": "participant_app.language",
        "pk": "Romanian",
        "fields": {}
    },
    {
        "model": "participant_app.language",
        "pk": "Azerbaijani",
        "fields": {}
    },
    {
        "model": "participant_app.language",
        "pk": "Awadhi",
        "fields": {}
    },
    {
        "model": "participant_app.language",
        "pk": "Gan",
        "fields": {}
    },
    {
        "model": "participant_app.language",
        "pk": "Cebuano (Visayan)",
        "fields": {}
    },
    {
        "model": "participant_app.language",
        "pk": "Dutch",
        "fields": {}
    },
    {
        "model": "participant_app.language",
        "pk": "Kurdish",
        "fields": {}
    },
    {
        "model": "participant_app.language",
        "pk": "Serbo-Croatian",
        "fields": {}
    },
    {
        "model": "participant_app.language",
        "pk": "Malagasy",
        "fields": {}
    },
    {
        "model": "participant_app.language",
        "pk": "Nepali",
        "fields": {}
    },
    {
        "model": "participant_app.language",
        "pk": "Saraiki",
        "fields": {}
    },
    {
        "model": "participant_app.language",
        "pk": "Chittagonian",
        "fields": {}
    },
    {
        "model": "participant_app.language",
        "pk": "Khmer",
        "fields": {}
    },
    {
        "model": "participant_app.language",
        "pk": "Sinhalese",
        "fields": {}
    },
    {
        "model": "participant_app.language",
        "pk": "Turkmen",
        "fields": {}
    },
    {
        "model": "participant_app.language",
        "pk": "Zhuang",
        "fields": {}
    },
    {
        "model": "participant_app.language",
        "pk": "Assamese",
        "fields": {}
    },
    {
        "model": "participant_app.language",
        "pk": "Madurese",
        "fields": {}
    },
    {
        "model": "participant_app.language",
        "pk": "Somali",
        "fields": {}
    },
    {
        "model": "participant_app.language",
        "pk": "Haryanvi",
        "fields": {}
    },
    {
        "model": "participant_app.language",
        "pk": "Magahi",
        "fields": {}
    },
    {
        "model": "participant_app.language",
        "pk": "Marwari",
        "fields": {}
    },
    {
        "model": "participant_app.language",
        "pk": "Hungarian",
        "fields": {}
    },
    {
        "model": "participant_app.language",
        "pk": "Chewa",
        "fields": {}
    },
    {
        "model": "participant_app.language",
        "pk": "Chhattisgarhi",
        "fields": {}
    },
    {
        "model": "participant_app.language",
        "pk": "Greek",
        "fields": {}
    },
    {
        "model": "participant_app.language",
        "pk": "Akan",
        "fields": {}
    },
    {
        "model": "participant_app.language",
        "pk": "Deccan",
        "fields": {}
    },
    {
        "model": "participant_app.language",
        "pk": "Kazakh",
        "fields": {}
    },
    {
        "model": "participant_app.language",
        "pk": "Northern Min",
        "fields": {}
    },
    {
        "model": "participant_app.language",
        "pk": "Sylheti",
        "fields": {}
    },
    {
        "model": "participant_app.language",
        "pk": "Zulu",
        "fields": {}
    },
    {
        "model": "participant_app.language",
        "pk": "Czech",
        "fields": {}
    },
    {
        "model": "participant_app.language",
        "pk": "Kinyarwanda",
        "fields": {}
    },
    {
        "model": "participant_app.language",
        "pk": "Dhundhari",
        "fields": {}
    },
    {
        "model": "participant_app.language",
        "pk": "Haitian Creole",
        "fields": {}
    },
    {
        "model": "participant_app.language",
        "pk": "Eastern Min (inc Fuzhou dialect)",
        "fields": {}
    },
    {
        "model": "participant_app.language",
        "pk": "Ilocano",
        "fields": {}
    },
    {
        "model": "participant_app.language",
        "pk": "Quechua",
        "fields": {}
    },
    {
        "model": "participant_app.language",
        "pk": "Kirundi",
        "fields": {}
    },
    {
        "model": "participant_app.language",
        "pk": "Swedish",
        "fields": {}
    },
    {
        "model": "participant_app.language",
        "pk": "Hmong",
        "fields": {}
    },
    {
        "model": "participant_app.language",
        "pk": "Shona",
        "fields": {}
    },
    {
        "model": "participant_app.language",
        "pk": "Hiligaynon/Ilonggo (Visayan)",
        "fields": {}
    },
    {
        "model": "participant_app.language",
        "pk": "Uyghur",
        "fields": {}
    },
    {
        "model": "participant_app.language",
        "pk": "Balochi",
        "fields": {}
    },
    {
        "model": "participant_app.language",
        "pk": "Belarusian",
        "fields": {}
    },
    {
        "model": "participant_app.language",
        "pk": "Mossi",
        "fields": {}
    },
    {
        "model": "participant_app.language",
        "pk": "Xhosa",
        "fields": {}
    },
    {
        "model": "participant_app.language",
        "pk": "Konkani",
        "fields": {}
    }
]